fc_mkdpy_bigdata.py
fc_mkdxd_bigdata-1.0.dist-info/METADATA
fc_mkdxd_bigdata-1.0.dist-info/WHEEL
fc_mkdxd_bigdata-1.0.dist-info/top_level.txt
fc_mkdxd_bigdata-1.0.dist-info/RECORD
