Metadata-Version: 2.1
Name: fc-mkdxd-bigdata
Version: 1.0
Summary: 毛坤铎
Home-page: UNKNOWN
Author: 大数据3
Author-email: fc@bigdata.com
License: UNKNOWN
Platform: UNKNOWN
